<annotation>
	<folder>3</folder>
	<filename>LHW5Ms4SEAGtveh5.png</filename>
	<path>/home/demir/Desktop/Veri/3/LHW5Ms4SEAGtveh5.png</path>
	<source>
		<database>Unknown</database>
	</source>
	<size>
		<width>300</width>
		<height>200</height>
		<depth>3</depth>
	</size>
	<segmented>0</segmented>
	<object>
		<name>Sol</name>
		<pose>Unspecified</pose>
		<truncated>1</truncated>
		<difficult>0</difficult>
		<bndbox>
			<xmin>45</xmin>
			<ymin>6</ymin>
			<xmax>300</xmax>
			<ymax>125</ymax>
		</bndbox>
	</object>
</annotation>
