<annotation>
	<folder>1</folder>
	<filename>LqxEdPczGbYd9Zlu.png</filename>
	<path>/home/demir/Desktop/Veri/1/LqxEdPczGbYd9Zlu.png</path>
	<source>
		<database>Unknown</database>
	</source>
	<size>
		<width>300</width>
		<height>200</height>
		<depth>3</depth>
	</size>
	<segmented>0</segmented>
	<object>
		<name>Sag</name>
		<pose>Unspecified</pose>
		<truncated>1</truncated>
		<difficult>0</difficult>
		<bndbox>
			<xmin>30</xmin>
			<ymin>5</ymin>
			<xmax>300</xmax>
			<ymax>161</ymax>
		</bndbox>
	</object>
</annotation>
